trapi_mcp/__init__.py
trapi_mcp/__main__.py
trapi_mcp/api_utilities.py
trapi_mcp/tools.py
trapi_mcp-0.1.3.dist-info/METADATA
trapi_mcp-0.1.3.dist-info/WHEEL
trapi_mcp-0.1.3.dist-info/entry_points.txt
trapi_mcp-0.1.3.dist-info/RECORD
