Metadata-Version: 2.4
Name: trapi-mcp
Version: 0.1.3
Summary: Add your description here
Project-URL: Homepage, https://github.com/smoxon/trapi-mcp
Project-URL: Bug Tracker, https://github.com/smoxon/trapi-mcp/issues
Requires-Python: >=3.11
Requires-Dist: fastmcp>=2.7.1
Requires-Dist: mcp>=1.9.3
Requires-Dist: requests>=2.32.4
